gitflow_linter/__init__.py
gitflow_linter/output.py
gitflow_linter/plugins.py
gitflow_linter/report.py
gitflow_linter/repository.py
gitflow_linter/rules.py
gitflow_linter/visitor.py
gitflow_linter-0.1.0.dist-info/LICENSE
gitflow_linter-0.1.0.dist-info/METADATA
gitflow_linter-0.1.0.dist-info/WHEEL
gitflow_linter-0.1.0.dist-info/entry_points.txt
gitflow_linter-0.1.0.dist-info/top_level.txt
gitflow_linter-0.1.0.dist-info/RECORD
