Metadata-Version: 2.1
Name: gitflow-linter
Version: 0.1.0
Summary: Checks if GitFlow is respected in a given repository, considering provided rules
Home-page: https://github.com/fighterpoul/gitflow_linter
Author: Poul Fighter
Author-email: fighter.poul@gmail.com
License: MIT
Platform: UNKNOWN
Classifier: License :: OSI Approved :: MIT License
Classifier: Programming Language :: Python :: 3.8
Requires-Python: >3.8
Requires-Dist: PyYAML (>=5.4.1)
Requires-Dist: GitPython (>=3.1.17)
Requires-Dist: click (>=7)
